dataflame/__init__.py
dataflame/version.py
dataflame/interpolation/__init__.py
dataflame/interpolation/utilities.py
dataflame/label_based_dataframe_alteration/__init__.py
dataflame/label_based_dataframe_alteration/utilities.py
dataflame/label_reformatting/__init__.py
dataflame/label_reformatting/utilities.py
dataflame/statistics/__init__.py
dataflame/statistics/numerification.py
dataflame/statistics/utilities.py
dataflame-1.0.6b0.dist-info/LICENSE.txt
dataflame-1.0.6b0.dist-info/METADATA
dataflame-1.0.6b0.dist-info/WHEEL
dataflame-1.0.6b0.dist-info/top_level.txt
dataflame-1.0.6b0.dist-info/RECORD
